{"cameraMode":{"drawMode":0,"name":"Shaded","section":"Shading Mode"},"sceneLighting":true,"audioPlay":false,"sceneViewState":{"m_AlwaysRefresh":false,"showFog":true,"showSkybox":true,"showFlares":true,"showImageEffects":true,"showParticleSystems":true,"showVisualEffectGraphs":true,"m_FxEnabled":true},"in2DMode":false,"pivot":{"x":-0.05917821079492569,"y":-0.873295783996582,"z":-0.3204679489135742},"rotation":{"x":-0.1571575254201889,"y":-0.0023737710434943439,"z":0.00037881359457969666,"w":-0.9875839352607727},"size":3.9874837398529054,"orthographic":false}